flogging/__init__.py
flogging/__main__.py
flogging/flogging.py
flogging/version.py
flogging/tests/__init__.py
flogging/tests/test_main.py
flogging-1.0.3.dist-info/licenses/LICENSE
flogging-1.0.3.dist-info/METADATA
flogging-1.0.3.dist-info/WHEEL
flogging-1.0.3.dist-info/top_level.txt
flogging-1.0.3.dist-info/RECORD
