Metadata-Version: 2.4
Name: flogging
Version: 1.0.3
Summary: flogging nice logging formatting and structured logging.
Home-page: 
Author: fragiletech
Author-email: gmarkhor@gmail.com
License: MIT
Keywords: logging
Classifier: Development Status :: 5 - Production/Stable
Classifier: Intended Audience :: Developers
Classifier: License :: OSI Approved :: MIT License
Classifier: Programming Language :: Python :: 3.10
Classifier: Topic :: Software Development :: Libraries
License-File: LICENSE
Requires-Dist: xxhash
Dynamic: author
Dynamic: author-email
Dynamic: classifier
Dynamic: description
Dynamic: description-content-type
Dynamic: keywords
Dynamic: license
Dynamic: license-file
Dynamic: requires-dist
Dynamic: summary
